spider/__init__.py
spider/fields.py
spider/models.py
spider/sanitizers.py
spider/sql_utils.py
spider/mysql/__init__.py
spider/mysql/connection.py
spider/mysql/exceptions.py
spider/sqlite/__init__.py
spider/sqlite/exceptions.py
spider/sqlite/sqlite_connection.py
spider/validators/__init__.py
spider/validators/_re.py
spider/validators/exceptions.py
spider/validators/fields_validations.py
tests/__init__.py
tests/func/__init__.py
tests/unit/__init__.py
tests/unit/test_models.py
tests/unit/test_sql_util.py
spider_orm-0.1.5.dist-info/LICENSE
spider_orm-0.1.5.dist-info/METADATA
spider_orm-0.1.5.dist-info/WHEEL
spider_orm-0.1.5.dist-info/top_level.txt
spider_orm-0.1.5.dist-info/RECORD
