Metadata-Version: 2.1
Name: spider-orm
Version: 0.1.5
Summary: Spider-ORM is a lightweight and flexible ORM (Object-Relational Mapping) library for Python.
Home-page: https://spider-orm.netlify.app/
Author: Simão Domingos de Oliveira António
Author-email: simaodomingos413@gmail.com
Classifier: Programming Language :: Python :: 3
Classifier: License :: OSI Approved :: MIT License
Classifier: Operating System :: OS Independent
Requires-Python: >=3.6
License-File: LICENSE
Requires-Dist: mysqlclient
Provides-Extra: dev
Requires-Dist: pytest>=3.7; extra == "dev"
Requires-Dist: sphinx; extra == "dev"
Requires-Dist: pytest-mock; extra == "dev"
Requires-Dist: coverage; extra == "dev"
